publish_demo/__init__.py
publish_demo/demo.py
publish_demo/divide.py
publish_demo-0.1.2.dist-info/METADATA
publish_demo-0.1.2.dist-info/WHEEL
publish_demo-0.1.2.dist-info/RECORD
