Metadata-Version: 2.1
Name: publish-demo
Version: 0.1.2
Summary: 
Author: darshanraval-crest
Author-email: darshan.raval@crestdatasys.com
Requires-Python: >=3.6,<4.0
Classifier: Programming Language :: Python :: 3
Classifier: Programming Language :: Python :: 3.6
Classifier: Programming Language :: Python :: 3.7
Classifier: Programming Language :: Python :: 3.8
Classifier: Programming Language :: Python :: 3.9
Classifier: Programming Language :: Python :: 3.10
Classifier: Programming Language :: Python :: 3.11
Requires-Dist: moviepy (>=1.0.3,<2.0.0)
Requires-Dist: pendulum (>=2.1.2,<3.0.0)
